rect_intersection/LICENSE
rect_intersection/README.MD
rect_intersection/__init__.py
rect_intersection/requirements.txt
rect_intersection/thirdparty.json
rect_intersection-0.10.dist-info/LICENSE.rst
rect_intersection-0.10.dist-info/METADATA
rect_intersection-0.10.dist-info/WHEEL
rect_intersection-0.10.dist-info/top_level.txt
rect_intersection-0.10.dist-info/RECORD
